LICENSE.txt
README.md
setup.py
FreeFortniteAPI/__init__.py
FreeFortniteAPI.egg-info/PKG-INFO
FreeFortniteAPI.egg-info/SOURCES.txt
FreeFortniteAPI.egg-info/dependency_links.txt
FreeFortniteAPI.egg-info/requires.txt
FreeFortniteAPI.egg-info/top_level.txt