Metadata-Version: 2.1
Name: FreeFortniteAPI
Version: 1.1.2
Summary: Easy to use FreeFortniteAPI module.
Home-page: 
Author: faktor
Author-email: minibots010@gmail.com
License: MIT
Keywords: FreeFortniteAPI
Classifier: License :: OSI Approved :: MIT License
Classifier: Intended Audience :: Developers
Classifier: Operating System :: OS Independent
Classifier: Programming Language :: Python :: 3.5
Classifier: Programming Language :: Python :: 3.6
Classifier: Programming Language :: Python :: 3.7
Classifier: Programming Language :: Python :: 3.8
Classifier: Programming Language :: Python :: 3.9
License-File: LICENSE.txt
